{
    "name": "Bhairav",
    "aaroh": ["S", "r", "G", "m", "P", "d", "N", "S'"],
    "avroh": ["S'", "N", "d", "P", "m", "G", "r", "S"],
    "motifs": [
        ["S", "r", "G"],
        ["G", "r", "S"],
        ["S", "N2", "S"],
        ["S", "r", "N2"],
        ["S", "G", "r", "G"],
        ["r", "G", "r", "S"],
        ["r", "G", "m", "G"],
        ["r", "G", "P", "G"],
        ["P", "m", "G", "r"],
        ["G", "r", "G", "m"],
        ["G", "r", "G", "P"],
        ["S", "r", "G", "S"],
        ["S", "G", "r", "S"],
        ["S", "G", "m", "P", "S"],
        ["S", "m", "P", "S"],
        ["S", "r", "G", "P", "S"],
        ["S", "r", "G", "m", "S"]
    ],
    "forbidden": ["R", "g", "D", "n", "M"]
   
}
